[{
  "name": "1.14",
  "mc": "1.14.4",
  "extractor": 0
}, {
  "name": "1.15",
  "mc": "1.15.1",
  "extractor": 0
}, {
  "name": "1.15.2",
  "mc": "1.15.2",
  "extractor": 0
}, {
  "name": "1.16",
  "mc": "1.16.1",
  "extractor": 0
}, {
  "name": "1.16.2",
  "mc": "1.16.5",
  "extractor": 0
}, {
  "name": "1.17",
  "mc": "1.17.1",
  "extractor": 1
}, {
  "name": "1.18",
  "mc": "1.18.2",
  "extractor": 1
}, {
  "name": "1.19",
  "mc": "1.19",
  "extractor": 1
}, {
  "name": "1.19.1",
  "mc": "1.19.2",
  "extractor": 1
}, {
  "name": "1.19.3",
  "mc": "1.19.3",
  "extractor": 2
}, {
  "name": "1.19.4",
  "mc": "1.19.4",
  "extractor": 2
}, {
  "name": "1.20",
  "mc": "1.20.1",
  "extractor": 3
}, {
  "name": "1.20.2",
  "mc": "1.20.2",
  "extractor": 3
}, {
  "name": "1.20.3",
  "mc": "1.20.4",
  "extractor": 3
}, {
  "name": "1.20.5",
  "mc": "1.20.6",
  "extractor": 3
},
{
  "name": "1.21",
  "mc": "1.21.1",
  "extractor": 3
}]
